<?xml version="1.0" encoding="UTF-8"?>
<entity-engine-xml>
    <ProductCategory longDescription="Milk Receipts "
        productCategoryId="MILK_RECEIPTS" categoryName="Milk Receipts" productCategoryTypeId="CATALOG_CATEGORY"/>
        
    <Product productId="R111" productTypeId="RAW_MATERIAL" primaryProductCategoryId="MILK_RECEIPTS" internalName="Buffalo Milk" productName="Buffalo Milk" brandName="BM WM" description="Buffalo Milk" longDescription="Buffalo Milk" quantityUomId="VLIQ_L"  taxable="N" chargeShipping="N" autoCreateKeywords="Y" isVirtual="N" isVariant="N" billOfMaterialLevel="0" createdDate="2011-12-01 12:00:00.0" lastModifiedDate="2011-12-01 12:00:00.0" lastModifiedByUserLogin="kvarma" inShippingBox="N" lastUpdatedStamp="2011-12-01 12:00:00.0" lastUpdatedTxStamp="2011-12-01 12:00:00.0" createdStamp="2011-12-01 12:00:00.0" createdTxStamp="2011-12-01 12:00:00.0"/>
    <ProductCategoryMember productCategoryId="MILK_RECEIPTS" productId="R111" fromDate="2011-12-01 12:00:00.0" lastUpdatedStamp="2012-01-10 18:53:58.0" lastUpdatedTxStamp="2012-01-10 18:53:57.0" createdStamp="2012-01-10 18:53:58.0" createdTxStamp="2012-01-10 18:53:57.0"/>
    
    <Product productId="R211" productTypeId="RAW_MATERIAL" primaryProductCategoryId="MILK_RECEIPTS" internalName="Cow Milk" productName="Cow Milk" brandName="CM WM" description="Cow Milk" longDescription="Cow Milk" quantityUomId="VLIQ_L"  taxable="N" chargeShipping="N" autoCreateKeywords="Y" isVirtual="N" isVariant="N" billOfMaterialLevel="0" createdDate="2011-12-01 12:00:00.0" lastModifiedDate="2011-12-01 12:00:00.0" lastModifiedByUserLogin="kvarma" inShippingBox="N" lastUpdatedStamp="2011-12-01 12:00:00.0" lastUpdatedTxStamp="2011-12-01 12:00:00.0" createdStamp="2011-12-01 12:00:00.0" createdTxStamp="2011-12-01 12:00:00.0"/>
    <ProductCategoryMember productCategoryId="MILK_RECEIPTS" productId="R211" fromDate="2011-12-01 12:00:00.0" lastUpdatedStamp="2012-01-10 18:53:58.0" lastUpdatedTxStamp="2012-01-10 18:53:57.0" createdStamp="2012-01-10 18:53:58.0" createdTxStamp="2012-01-10 18:53:57.0"/>
    
    <Product productId="R333" productTypeId="RAW_MATERIAL" primaryProductCategoryId="MILK_RECEIPTS" internalName="Mixed Milk" productName="Mixed Milk" brandName="MM WM" description="Mixed Milk" longDescription="Mixed Milk" quantityUomId="VLIQ_L"  taxable="N" chargeShipping="N" autoCreateKeywords="Y" isVirtual="N" isVariant="N" billOfMaterialLevel="0" createdDate="2011-12-01 12:00:00.0" lastModifiedDate="2011-12-01 12:00:00.0" lastModifiedByUserLogin="kvarma" inShippingBox="N" lastUpdatedStamp="2011-12-01 12:00:00.0" lastUpdatedTxStamp="2011-12-01 12:00:00.0" createdStamp="2011-12-01 12:00:00.0" createdTxStamp="2011-12-01 12:00:00.0"/>
    <ProductCategoryMember productCategoryId="MILK_RECEIPTS" productId="R333" fromDate="2011-12-01 12:00:00.0" lastUpdatedStamp="2012-01-10 18:53:58.0" lastUpdatedTxStamp="2012-01-10 18:53:57.0" createdStamp="2012-01-10 18:53:58.0" createdTxStamp="2012-01-10 18:53:57.0"/>
    
    <Product productId="R121" productTypeId="RAW_MATERIAL" primaryProductCategoryId="MILK_RECEIPTS" internalName="Buffalo Skim Milk" productName="Buffalo Skim Milk" brandName="BM SKM" description="Buffalo Skim Milk" longDescription="Buffalo Skim Milk" quantityUomId="VLIQ_L"  taxable="N" chargeShipping="N" autoCreateKeywords="Y" isVirtual="N" isVariant="N" billOfMaterialLevel="0" createdDate="2011-12-01 12:00:00.0" lastModifiedDate="2011-12-01 12:00:00.0" lastModifiedByUserLogin="kvarma" inShippingBox="N" lastUpdatedStamp="2011-12-01 12:00:00.0" lastUpdatedTxStamp="2011-12-01 12:00:00.0" createdStamp="2011-12-01 12:00:00.0" createdTxStamp="2011-12-01 12:00:00.0"/>
    <ProductCategoryMember productCategoryId="MILK_RECEIPTS" productId="R121" fromDate="2011-12-01 12:00:00.0" lastUpdatedStamp="2012-01-10 18:53:58.0" lastUpdatedTxStamp="2012-01-10 18:53:57.0" createdStamp="2012-01-10 18:53:58.0" createdTxStamp="2012-01-10 18:53:57.0"/>
    
    <Product productId="R221" productTypeId="RAW_MATERIAL" primaryProductCategoryId="MILK_RECEIPTS" internalName="Cow Skim Milk" productName="Cow Skim Milk" brandName="CM SKM" description="Cow Skim Milk" longDescription="Cow Skim Milk" quantityUomId="VLIQ_L"  taxable="N" chargeShipping="N" autoCreateKeywords="Y" isVirtual="N" isVariant="N" billOfMaterialLevel="0" createdDate="2011-12-01 12:00:00.0" lastModifiedDate="2011-12-01 12:00:00.0" lastModifiedByUserLogin="kvarma" inShippingBox="N" lastUpdatedStamp="2011-12-01 12:00:00.0" lastUpdatedTxStamp="2011-12-01 12:00:00.0" createdStamp="2011-12-01 12:00:00.0" createdTxStamp="2011-12-01 12:00:00.0"/>
    <ProductCategoryMember productCategoryId="MILK_RECEIPTS" productId="R221" fromDate="2011-12-01 12:00:00.0" lastUpdatedStamp="2012-01-10 18:53:58.0" lastUpdatedTxStamp="2012-01-10 18:53:57.0" createdStamp="2012-01-10 18:53:58.0" createdTxStamp="2012-01-10 18:53:57.0"/>
    
    <Product productId="R999" productTypeId="RAW_MATERIAL" primaryProductCategoryId="MILK_RECEIPTS" internalName="Sour Milk" productName="Sour Milk" brandName="SOUR/REJT" description="Sour Milk" longDescription="Sour Milk" quantityUomId="VLIQ_L"  taxable="N" chargeShipping="N" autoCreateKeywords="Y" isVirtual="N" isVariant="N" billOfMaterialLevel="0" createdDate="2011-12-01 12:00:00.0" lastModifiedDate="2011-12-01 12:00:00.0" lastModifiedByUserLogin="kvarma" inShippingBox="N" lastUpdatedStamp="2011-12-01 12:00:00.0" lastUpdatedTxStamp="2011-12-01 12:00:00.0" createdStamp="2011-12-01 12:00:00.0" createdTxStamp="2011-12-01 12:00:00.0"/>
    <ProductCategoryMember productCategoryId="MILK_RECEIPTS" productId="R999" fromDate="2011-12-01 12:00:00.0" lastUpdatedStamp="2012-01-10 18:53:58.0" lastUpdatedTxStamp="2012-01-10 18:53:57.0" createdStamp="2012-01-10 18:53:58.0" createdTxStamp="2012-01-10 18:53:57.0"/>
    
    
    
    
    
    <Product productId="R444" productTypeId="RAW_MATERIAL" primaryProductCategoryId="MILK_RECEIPTS" internalName="Toned Milk" productName="Toned Milk" brandName="TM" description="Toned Milk" longDescription="Toned Milk" quantityUomId="VLIQ_L"  taxable="N" chargeShipping="N" autoCreateKeywords="Y" isVirtual="N" isVariant="N" billOfMaterialLevel="0" createdDate="2011-12-01 12:00:00.0" lastModifiedDate="2011-12-01 12:00:00.0" lastModifiedByUserLogin="kvarma" inShippingBox="N" lastUpdatedStamp="2011-12-01 12:00:00.0" lastUpdatedTxStamp="2011-12-01 12:00:00.0" createdStamp="2011-12-01 12:00:00.0" createdTxStamp="2011-12-01 12:00:00.0"/>
    <ProductCategoryMember productCategoryId="MILK_RECEIPTS" productId="R444" fromDate="2011-12-01 12:00:00.0" lastUpdatedStamp="2012-01-10 18:53:58.0" lastUpdatedTxStamp="2012-01-10 18:53:57.0" createdStamp="2012-01-10 18:53:58.0" createdTxStamp="2012-01-10 18:53:57.0"/>
    
    <ProductCategoryMember productCategoryId="MILK_RECEIPTS" productId="101" fromDate="2011-12-01 12:00:00.0" lastUpdatedStamp="2012-01-10 18:53:58.0" lastUpdatedTxStamp="2012-01-10 18:53:57.0" createdStamp="2012-01-10 18:53:58.0" createdTxStamp="2012-01-10 18:53:57.0"/>
    <ProductCategoryMember productCategoryId="MILK_RECEIPTS" productId="102" fromDate="2011-12-01 12:00:00.0" lastUpdatedStamp="2012-01-10 18:53:58.0" lastUpdatedTxStamp="2012-01-10 18:53:57.0" createdStamp="2012-01-10 18:53:58.0" createdTxStamp="2012-01-10 18:53:57.0"/>
    <ProductCategoryMember productCategoryId="MILK_RECEIPTS" productId="103" fromDate="2011-12-01 12:00:00.0" lastUpdatedStamp="2012-01-10 18:53:58.0" lastUpdatedTxStamp="2012-01-10 18:53:57.0" createdStamp="2012-01-10 18:53:58.0" createdTxStamp="2012-01-10 18:53:57.0"/>
	<FacilityAttribute facilityId="KRNT" attrName="enableQuantityKgs" attrValue="Y"/>
	
	
	<Facility facilityId="ANTP" mccTypeId="FEDERATION"></Facility>
	<Facility facilityId="CHTR" mccTypeId="FEDERATION"></Facility>
	<Facility facilityId="EGD" mccTypeId="FEDERATION"></Facility>
	<Facility facilityId="KDP" mccTypeId="FEDERATION"></Facility>
	<Facility facilityId="KMM" mccTypeId="FEDERATION"></Facility>
	<Facility facilityId="MBNR" mccTypeId="FEDERATION"></Facility>
	<Facility facilityId="MDK" mccTypeId="FEDERATION"></Facility>
	<Facility facilityId="NLG" mccTypeId="FEDERATION"></Facility>
	<Facility facilityId="NZB" mccTypeId="FEDERATION"></Facility>
	<Facility facilityId="WGD" mccTypeId="FEDERATION"></Facility>
	<Facility facilityId="WGL" mccTypeId="FEDERATION"></Facility>
	
	
	<Facility facilityId="VZG" mccTypeId="UNION"></Facility>
	<Facility facilityId="VFD" mccTypeId="UNION"></Facility>
	<Facility facilityId="TMLN" mccTypeId="UNION"></Facility>
	<Facility facilityId="PRA" mccTypeId="UNION"></Facility>
	<Facility facilityId="ORIS" mccTypeId="UNION"></Facility>
	<Facility facilityId="NLR" mccTypeId="UNION"></Facility>
	<Facility facilityId="MAHR" mccTypeId="UNION"></Facility>
	<Facility facilityId="KRNT" mccTypeId="UNION"></Facility>
	<Facility facilityId="KRL" mccTypeId="UNION"></Facility>
	<Facility facilityId="KRI" mccTypeId="UNION"></Facility>
	<Facility facilityId="KNG" mccTypeId="UNION"></Facility>
	<Facility facilityId="KKN" mccTypeId="UNION"></Facility>
	<Facility facilityId="GUN" mccTypeId="UNION"></Facility>
	<Facility facilityId="PVT" mccTypeId="OTHERS"></Facility>
	
	<!-- contactList example -->
	<ContactList contactListId="ANDHRA_NOTIFY_LST" contactListName="ANDHRA NOTIFY LIST"  description="ANDHRA NOTIFY LIST"
				 contactListTypeId="ANNOUNCEMENT" contactMechTypeId="TELECOM_NUMBER" ownerPartyId="10200" />
	<ContactList contactListId="RECPT_NOTIFY_LST" contactListName="RECEIPTS NOTIFY LIST"  description="RECEIPTS NOTIFY LIST"
				 contactListTypeId="ANNOUNCEMENT" contactMechTypeId="TELECOM_NUMBER" ownerPartyId="10200" />
				 
	<Enumeration enumId="INTERNAL" enumCode="IDR" description="Internal Dairy Pupose" enumTypeId="MILK_PRCH_PURP" sequenceId="1"></Enumeration>
	<Enumeration enumId="CONVERSION" enumCode="CONVERSION" description="Conversion Purpose" enumTypeId="MILK_PRCH_PURP" sequenceId="2"></Enumeration>
		
		
	<EnumerationType enumTypeId="MILK_OUT_PURP" description="Milk Outgoing Purpose" hasTable="N"></EnumerationType>
	<Enumeration enumId="INTERNALUSE" enumCode="INTERNAL SECTION" description="Internal Use" enumTypeId="MILK_OUT_PURP" sequenceId="1"></Enumeration>
	<Enumeration enumId="OUTGOING" enumCode="OUT GOING TANKER" description="Out going tanker" enumTypeId="MILK_OUT_PURP" sequenceId="2"></Enumeration>
	<Enumeration enumId="COPACKING" enumCode="Co Packing  TANKER" description="Copacking tanker" enumTypeId="MILK_OUT_PURP" sequenceId="3"></Enumeration>
	
	<FacilityPartyRate partyId="MAN" facilityId="_NA_" 
	fromDate="2014-05-11 00:00:00.0"   productId="_NA_" rateAmount="154" 
	rateCurrencyUomId="INR" rateTypeId="DISTANCE_FROM_MD" supplyTypeEnumId="_NA_" />
	
	<RateType rateTypeId="PTC_RATE" description="Ptc Rate"/>
	<FacilityPartyRate partyId="MAN" facilityId="_NA_" acctgFormulaId="PTC_MAN"
	fromDate="2014-05-11 00:00:00.0"   productId="_NA_" rateAmount="0" 
	rateCurrencyUomId="INR" rateTypeId="PTC_RATE" supplyTypeEnumId="_NA_" />
	
	<AcctgFormula acctgFormulaId="PTC_MAN"  description="PTC MAN " isSlabBased="Y"/>
	<AcctgFormulaSlabs acctgFormulaId="PTC_MAN" slabStart="0" slabEnd="9270" formula="26.7*${DISTANCE}*${QUANTITYKGS}/${CAPACITY}" description="PTC CALCULATION FOR MAN"/>
	<AcctgFormulaSlabs acctgFormulaId="PTC_MAN" slabStart="9271" slabEnd="99999" formula="28.3*${DISTANCE}*${QUANTITYKGS}/${CAPACITY}" description="PTC CALCULATION FOR MAN"/>
	
	<RoleType roleTypeId="CHILL_CENTER" hasTable="N" description="Chilling Center"/>
	<PartyRole partyId="SAD" roleTypeId="CHILL_CENTER" fromDate ="2015-01-01 00:00:00" />
	<PartyRole partyId="GOW" roleTypeId="CHILL_CENTER" fromDate ="2015-01-01 00:00:00" />
	
	<PartyRelationship partyIdFrom="KMU" partyIdTo="SAD" roleTypeIdFrom="UNION" roleTypeIdTo="CHILL_CENTER" fromDate="2015-01-01 00:00:00"/>
	<PartyRelationship partyIdFrom="KMU" partyIdTo="GOW" roleTypeIdFrom="UNION" roleTypeIdTo="CHILL_CENTER" fromDate="2015-01-01 00:00:00"/>
	
	
	<RateType rateTypeId="PTC_RATE" description="Ptc Rate"/>
	<FacilityPartyRate partyId="SAD" facilityId="_NA_" acctgFormulaId=""
	fromDate="2014-05-11 00:00:00.0"   productId="_NA_" rateAmount="0.40" 
	rateCurrencyUomId="INR" rateTypeId="PTC_RATE" supplyTypeEnumId="_NA_" />
	
	
	
	<FacilityPartyRate partyId="KMU" facilityId="_NA_" acctgFormulaId=""
	fromDate="2014-05-11 00:00:00.0"   productId="_NA_" rateAmount="0.40" 
	rateCurrencyUomId="INR" rateTypeId="PTC_RATE" supplyTypeEnumId="_NA_" />
	
	<FacilityPartyRate partyId="SAD" facilityId="_NA_" 
	fromDate="2014-05-11 00:00:00.0"   productId="_NA_" rateAmount="114" 
	rateCurrencyUomId="INR" rateTypeId="DISTANCE_FROM_MD" supplyTypeEnumId="_NA_" />
	<FacilityPartyRate partyId="GOW" facilityId="_NA_" 
	fromDate="2014-05-11 00:00:00.0"   productId="_NA_" rateAmount="120" 
	rateCurrencyUomId="INR" rateTypeId="DISTANCE_FROM_MD" supplyTypeEnumId="_NA_" />
	
	
	
	
</entity-engine-xml>