<?xml version="1.0" encoding="UTF-8"?>

<entity-engine-xml>
    <InvoiceItem invoiceId="SHP_SCRP_SEP_01" invoiceItemSeqId="0001" invoiceItemTypeId="INV_FPROD_ITEM" quantity="1" amount="1500" description="Scrap/Deepfreezer Sales Book As on SEP-30-2014" taxAuthorityPartyId="NULL"/>
    <InvoiceItem invoiceId="SHP_SCRP_SEP_02" invoiceItemSeqId="0001" invoiceItemTypeId="INV_FPROD_ITEM" quantity="1" amount="3000" description="Scrap/Deepfreezer Sales Book As on SEP-30-2014" taxAuthorityPartyId="NULL"/>
    <InvoiceItem invoiceId="SHP_SCRP_SEP_03" invoiceItemSeqId="0001" invoiceItemTypeId="INV_FPROD_ITEM" quantity="1" amount="3646" description="Scrap/Deepfreezer Sales Book As on SEP-30-2014" taxAuthorityPartyId="NULL"/>
    <InvoiceItem invoiceId="SHP_SCRP_SEP_04" invoiceItemSeqId="0001" invoiceItemTypeId="INV_FPROD_ITEM" quantity="1" amount="1500" description="Scrap/Deepfreezer Sales Book As on SEP-30-2014" taxAuthorityPartyId="NULL"/>
    <InvoiceItem invoiceId="SHP_SCRP_SEP_05" invoiceItemSeqId="0001" invoiceItemTypeId="INV_FPROD_ITEM" quantity="1" amount="1500" description="Scrap/Deepfreezer Sales Book As on SEP-30-2014" taxAuthorityPartyId="NULL"/>
    <InvoiceItem invoiceId="SHP_SCRP_SEP_06" invoiceItemSeqId="0001" invoiceItemTypeId="INV_FPROD_ITEM" quantity="1" amount="640" description="Scrap/Deepfreezer Sales Book As on SEP-30-2014" taxAuthorityPartyId="NULL"/>
    <InvoiceItem invoiceId="SHP_SCRP_SEP_07" invoiceItemSeqId="0001" invoiceItemTypeId="INV_FPROD_ITEM" quantity="1" amount="6555" description="Scrap/Deepfreezer Sales Book As on SEP-30-2014" taxAuthorityPartyId="NULL"/>
    <InvoiceItem invoiceId="SHP_SCRP_SEP_08" invoiceItemSeqId="0001" invoiceItemTypeId="INV_FPROD_ITEM" quantity="1" amount="3000" description="Scrap/Deepfreezer Sales Book As on SEP-30-2014" taxAuthorityPartyId="NULL"/>
    <InvoiceItem invoiceId="SHP_SCRP_SEP_09" invoiceItemSeqId="0001" invoiceItemTypeId="INV_FPROD_ITEM" quantity="1" amount="710" description="Scrap/Deepfreezer Sales Book As on SEP-30-2014" taxAuthorityPartyId="NULL"/>
    <InvoiceItem invoiceId="SHP_SCRP_SEP_10" invoiceItemSeqId="0001" invoiceItemTypeId="INV_FPROD_ITEM" quantity="1" amount="11400" description="Scrap/Deepfreezer Sales Book As on SEP-30-2014" taxAuthorityPartyId="NULL"/>
    <InvoiceItem invoiceId="SHP_SCRP_SEP_11" invoiceItemSeqId="0001" invoiceItemTypeId="INV_FPROD_ITEM" quantity="1" amount="4260" description="Scrap/Deepfreezer Sales Book As on SEP-30-2014" taxAuthorityPartyId="NULL"/>
</entity-engine-xml>
