<ProductCategoryAttribute productCategoryId="AAVINDELITE_CAT" attrName="UNION_TAXABLE" attrValue="0" lastUpdatedStamp="2013-05-08 11:10:49.0" lastUpdatedTxStamp="2013-05-08 11:10:49.0" createdStamp="2013-05-08 10:41:10.0" createdTxStamp="2013-05-08 10:41:10.0"/>
    <ProductCategoryAttribute productCategoryId="AAVIN_CHOC_CAT" attrName="DAIRY_TAXABLE" attrValue="14.5" lastUpdatedStamp="2013-05-08 11:10:49.0" lastUpdatedTxStamp="2013-05-08 11:10:49.0" createdStamp="2013-05-08 10:41:10.0" createdTxStamp="2013-05-08 10:41:10.0"/>
    <ProductCategoryAttribute productCategoryId="AAVIN_SPORTY_CAT" attrName="UNION_TAXABLE" attrValue="5" lastUpdatedStamp="2013-05-08 11:10:49.0" lastUpdatedTxStamp="2013-05-08 11:10:49.0" createdStamp="2013-05-08 10:41:10.0" createdTxStamp="2013-05-08 10:41:10.0"/>
    <ProductCategoryAttribute productCategoryId="BADAM_MILK_CAT" attrName="DAIRY_TAXABLE" attrValue="0" lastUpdatedStamp="2013-05-08 11:10:49.0" lastUpdatedTxStamp="2013-05-08 11:10:49.0" createdStamp="2013-05-08 10:41:10.0" createdTxStamp="2013-05-08 10:41:10.0"/>
    <ProductCategoryAttribute productCategoryId="BADAM_POWDER_CAT" attrName="UNION_TAXABLE" attrValue="14.5" lastUpdatedStamp="2013-05-08 11:10:49.0" lastUpdatedTxStamp="2013-05-08 11:10:49.0" createdStamp="2013-05-08 10:41:10.0" createdTxStamp="2013-05-08 10:41:10.0"/>
    <ProductCategoryAttribute productCategoryId="BUTTER_C_CAT" attrName="UNION_TAXABLE" attrValue="14.5" lastUpdatedStamp="2013-05-08 11:10:49.0" lastUpdatedTxStamp="2013-05-08 11:10:49.0" createdStamp="2013-05-08 10:41:10.0" createdTxStamp="2013-05-08 10:41:10.0"/>
    <ProductCategoryAttribute productCategoryId="BUTTER_MILK_CAT" attrName="DAIRY_TAXABLE" attrValue="0" lastUpdatedStamp="2013-05-08 11:10:49.0" lastUpdatedTxStamp="2013-05-08 11:10:49.0" createdStamp="2013-05-08 10:41:10.0" createdTxStamp="2013-05-08 10:41:10.0"/>
    <ProductCategoryAttribute productCategoryId="BUTTER_T_CAT" attrName="UNION_TAXABLE" attrValue="14.5" lastUpdatedStamp="2013-05-08 11:10:49.0" lastUpdatedTxStamp="2013-05-08 11:10:49.0" createdStamp="2013-05-08 10:41:10.0" createdTxStamp="2013-05-08 10:41:10.0"/>
    <ProductCategoryAttribute productCategoryId="CHEESE_CAT" attrName="UNION_TAXABLE" attrValue="14.5" lastUpdatedStamp="2013-05-08 11:10:49.0" lastUpdatedTxStamp="2013-05-08 11:10:49.0" createdStamp="2013-05-08 10:41:10.0" createdTxStamp="2013-05-08 10:41:10.0"/>
    <ProductCategoryAttribute productCategoryId="CHILLY_CHEESE_CAT" attrName="DAIRY_TAXABLE" attrValue="0" lastUpdatedStamp="2013-05-08 11:10:49.0" lastUpdatedTxStamp="2013-05-08 11:10:49.0" createdStamp="2013-05-08 10:41:10.0" createdTxStamp="2013-05-08 10:41:10.0"/>
    <ProductCategoryAttribute productCategoryId="CURD_CAT" attrName="DAIRY_TAXABLE" attrValue="0" lastUpdatedStamp="2013-05-08 11:10:49.0" lastUpdatedTxStamp="2013-05-08 11:10:49.0" createdStamp="2013-05-08 11:10:49.0" createdTxStamp="2013-05-08 11:10:49.0"/>
    <ProductCategoryAttribute productCategoryId="FMB_CAT" attrName="DAIRY_TAXABLE" attrValue="0" lastUpdatedStamp="2013-05-08 11:10:49.0" lastUpdatedTxStamp="2013-05-08 11:10:49.0" createdStamp="2013-05-08 11:10:49.0" createdTxStamp="2013-05-08 11:10:49.0"/>
    <ProductCategoryAttribute productCategoryId="FM_CAT" attrName="UNION_TAXABLE" attrValue="5" lastUpdatedStamp="2013-05-08 11:10:49.0" lastUpdatedTxStamp="2013-05-08 11:10:49.0" createdStamp="2013-05-08 10:41:10.0" createdTxStamp="2013-05-08 10:41:10.0"/>
    <ProductCategoryAttribute productCategoryId="GHEE_CAT" attrName="UNION_TAXABLE" attrValue="5" lastUpdatedStamp="2013-05-08 11:10:49.0" lastUpdatedTxStamp="2013-05-08 11:10:49.0" createdStamp="2013-05-08 10:41:10.0" createdTxStamp="2013-05-08 10:41:10.0"/>
    <ProductCategoryAttribute productCategoryId="GULABJAMUN_CAT" attrName="DAIRY_TAXABLE" attrValue="5" lastUpdatedStamp="2013-05-08 11:10:49.0" lastUpdatedTxStamp="2013-05-08 11:10:49.0" createdStamp="2013-05-08 11:10:49.0" createdTxStamp="2013-05-08 11:10:49.0"/>
    <ProductCategoryAttribute productCategoryId="HOT_MILK_CAT" attrName="DAIRY_TAXABLE" attrValue="0" lastUpdatedStamp="2013-05-08 11:10:49.0" lastUpdatedTxStamp="2013-05-08 11:10:49.0" createdStamp="2013-05-08 11:10:49.0" createdTxStamp="2013-05-08 11:10:49.0"/>
    <ProductCategoryAttribute productCategoryId="ICECREAM_CAT" attrName="DAIRY_TAXABLE" attrValue="14.5" lastUpdatedStamp="2013-05-08 11:10:49.0" lastUpdatedTxStamp="2013-05-08 11:10:49.0" createdStamp="2013-05-08 11:10:49.0" createdTxStamp="2013-05-08 11:10:49.0"/>
    <ProductCategoryAttribute productCategoryId="KHOVA_CAT" attrName="DAIRY_TAXABLE" attrValue="5" lastUpdatedStamp="2013-05-08 11:10:49.0" lastUpdatedTxStamp="2013-05-08 11:10:49.0" createdStamp="2013-05-08 11:10:49.0" createdTxStamp="2013-05-08 11:10:49.0"/>
    <ProductCategoryAttribute productCategoryId="LASSI_CAT" attrName="DAIRY_TAXABLE" attrValue="0" lastUpdatedStamp="2013-05-08 11:10:49.0" lastUpdatedTxStamp="2013-05-08 11:10:49.0" createdStamp="2013-05-08 11:10:49.0" createdTxStamp="2013-05-08 11:10:49.0"/>
    <ProductCategoryAttribute productCategoryId="MAAVIN_CAT" attrName="UNION_TAXABLE" attrValue="5" lastUpdatedStamp="2013-05-08 11:10:49.0" lastUpdatedTxStamp="2013-05-08 11:10:49.0" createdStamp="2013-05-08 10:41:10.0" createdTxStamp="2013-05-08 10:41:10.0"/>
    <ProductCategoryAttribute productCategoryId="MILK_BREAD_CAT" attrName="UNION_TAXABLE" attrValue="5" lastUpdatedStamp="2013-05-08 11:10:49.0" lastUpdatedTxStamp="2013-05-08 11:10:49.0" createdStamp="2013-05-08 10:41:10.0" createdTxStamp="2013-05-08 10:41:10.0"/>
    <ProductCategoryAttribute productCategoryId="MILK_SHAKE_CAT" attrName="DAIRY_TAXABLE" attrValue="0" lastUpdatedStamp="2013-05-08 11:10:49.0" lastUpdatedTxStamp="2013-05-08 11:10:49.0" createdStamp="2013-05-08 11:10:49.0" createdTxStamp="2013-05-08 11:10:49.0"/>
    <ProductCategoryAttribute productCategoryId="MTP_CAT" attrName="UNION_TAXABLE" attrValue="5" lastUpdatedStamp="2013-05-08 11:10:49.0" lastUpdatedTxStamp="2013-05-08 11:10:49.0" createdStamp="2013-05-08 10:41:10.0" createdTxStamp="2013-05-08 10:41:10.0"/>
    <ProductCategoryAttribute productCategoryId="MYSOREPAK_CAT" attrName="DAIRY_TAXABLE" attrValue="5" lastUpdatedStamp="2013-05-08 11:10:49.0" lastUpdatedTxStamp="2013-05-08 11:10:49.0" createdStamp="2013-05-08 11:10:49.0" createdTxStamp="2013-05-08 11:10:49.0"/>
    <ProductCategoryAttribute productCategoryId="M_MILKSHAKE_CAT" attrName="UNION_TAXABLE" attrValue="5" lastUpdatedStamp="2013-05-08 11:10:49.0" lastUpdatedTxStamp="2013-05-08 11:10:49.0" createdStamp="2013-05-08 10:41:10.0" createdTxStamp="2013-05-08 10:41:10.0"/>
    <ProductCategoryAttribute productCategoryId="OOTYTEA_CAT" attrName="DAIRY_TAXABLE" attrValue="5" lastUpdatedStamp="2013-05-08 11:10:49.0" lastUpdatedTxStamp="2013-05-08 11:10:49.0" createdStamp="2013-05-08 11:10:49.0" createdTxStamp="2013-05-08 11:10:49.0"/>
    <ProductCategoryAttribute productCategoryId="PANNER_CAT" attrName="DAIRY_TAXABLE" attrValue="5" lastUpdatedStamp="2013-05-08 11:10:49.0" lastUpdatedTxStamp="2013-05-08 11:10:49.0" createdStamp="2013-05-08 11:10:49.0" createdTxStamp="2013-05-08 11:10:49.0"/>
    <ProductCategoryAttribute productCategoryId="PIZZA_CAT" attrName="DAIRY_TAXABLE" attrValue="0" lastUpdatedStamp="2013-05-08 11:10:49.0" lastUpdatedTxStamp="2013-05-08 11:10:49.0" createdStamp="2013-05-08 11:10:49.0" createdTxStamp="2013-05-08 11:10:49.0"/>
    <ProductCategoryAttribute productCategoryId="SMP_CAT" attrName="UNION_TAXABLE" attrValue="5" lastUpdatedStamp="2013-05-08 11:10:49.0" lastUpdatedTxStamp="2013-05-08 11:10:49.0" createdStamp="2013-05-08 10:41:10.0" createdTxStamp="2013-05-08 10:41:10.0"/>
    <ProductCategoryAttribute productCategoryId="YOGHURT_CAT" attrName="DAIRY_TAXABLE" attrValue="14.5" lastUpdatedStamp="2013-05-08 11:10:49.0" lastUpdatedTxStamp="2013-05-08 11:10:49.0" createdStamp="2013-05-08 11:10:49.0" createdTxStamp="2013-05-08 11:10:49.0"/>
	
	<!-- DKMUL      -->
    <ProductCategoryType createdStamp="2013-10-09 22:24:16.0" createdTxStamp="2013-10-09 22:24:16.0" description="PRODUCT INDENT CATEGORY" lastUpdatedStamp="2013-10-09 22:24:16.0" lastUpdatedTxStamp="2013-10-09 22:24:16.0" productCategoryTypeId="PROD_INDENT_CAT"/>
    <ProductCategory createdStamp="2013-10-08 23:04:46.0" createdTxStamp="2013-10-08 23:04:46.0" description="Packet indent" lastUpdatedStamp="2013-10-09 22:26:24.0" lastUpdatedTxStamp="2013-10-09 22:26:24.0" productCategoryId="PACKET_INDENT" productCategoryTypeId="PROD_INDENT_CAT"/>
     <ProductCategory createdStamp="2013-10-08 23:04:46.0" createdTxStamp="2013-10-08 23:04:46.0" description="Crate indent" lastUpdatedStamp="2013-10-09 22:26:07.0" lastUpdatedTxStamp="2013-10-09 22:26:07.0" productCategoryId="CRATE_INDENT" productCategoryTypeId="PROD_INDENT_CAT"/>
</entity-engine-xml>